alea_llm_client/__init__.py
alea_llm_client/core/__init__.py
alea_llm_client/core/exceptions.py
alea_llm_client/core/logging/__init__.py
alea_llm_client/core/logging/logger.py
alea_llm_client/core/logging/mixin.py
alea_llm_client/llms/__init__.py
alea_llm_client/llms/model_capabilities.py
alea_llm_client/llms/model_registry.py
alea_llm_client/llms/config/__init__.py
alea_llm_client/llms/config/loader.py
alea_llm_client/llms/config/models.json
alea_llm_client/llms/constants/__init__.py
alea_llm_client/llms/constants/anthropic_models.py
alea_llm_client/llms/constants/grammar_constants.py
alea_llm_client/llms/constants/openai_models.py
alea_llm_client/llms/models/__init__.py
alea_llm_client/llms/models/anthropic_model.py
alea_llm_client/llms/models/base_ai_model.py
alea_llm_client/llms/models/google_model.py
alea_llm_client/llms/models/grok_model.py
alea_llm_client/llms/models/openai_compatible_model.py
alea_llm_client/llms/models/openai_model.py
alea_llm_client/llms/models/vllm_model.py
alea_llm_client/llms/prompts/__init__.py
alea_llm_client/llms/prompts/formatters.py
alea_llm_client/llms/prompts/sections.py
alea_llm_client/llms/utils/__init__.py
alea_llm_client/llms/utils/api_keys.py
alea_llm_client/llms/utils/json.py
alea_llm_client-0.2.3.dist-info/METADATA
alea_llm_client-0.2.3.dist-info/WHEEL
alea_llm_client-0.2.3.dist-info/licenses/LICENSE
alea_llm_client-0.2.3.dist-info/RECORD
