Metadata-Version: 2.4
Name: alea-llm-client
Version: 0.2.3
Summary: ALEA LLM client abstraction library for Python
Project-URL: Homepage, https://aleainstitute.ai/
Project-URL: Repository, https://github.com/alea-institute/alea-llm-client
Author-email: ALEA Institute <hello@aleainstitute.ai>
License-Expression: MIT
License-File: LICENSE
Keywords: alea,api,client,llm
Classifier: Development Status :: 3 - Alpha
Classifier: Intended Audience :: Developers
Classifier: Intended Audience :: Science/Research
Classifier: License :: OSI Approved :: MIT License
Classifier: Operating System :: OS Independent
Classifier: Programming Language :: Python
Classifier: Programming Language :: Python :: 3
Classifier: Programming Language :: Python :: 3.10
Classifier: Programming Language :: Python :: 3.11
Classifier: Programming Language :: Python :: 3.12
Classifier: Programming Language :: Python :: 3.13
Classifier: Topic :: Scientific/Engineering :: Artificial Intelligence
Classifier: Topic :: Scientific/Engineering :: Information Analysis
Classifier: Topic :: Software Development :: Libraries :: Python Modules
Classifier: Topic :: Utilities
Requires-Python: <4.0.0,>=3.9
Requires-Dist: httpx[http2]>=0.28.1
Requires-Dist: pydantic>=2.9.1
